flaskosql/__init__.py
flaskosql/db.py
flaskosql/field.py
flaskosql/main.py
flaskosql/model.py
flaskosql-2.1.4.dist-info/LICENSE
flaskosql-2.1.4.dist-info/METADATA
flaskosql-2.1.4.dist-info/WHEEL
flaskosql-2.1.4.dist-info/top_level.txt
flaskosql-2.1.4.dist-info/RECORD
