Metadata-Version: 2.1
Name: flaskosql
Version: 2.1.4
Summary: ORM to databases for FLASK API
Author: Ashraf khabar
Author-email: <khabarachraf@gmail.com>
Keywords: python,orm,api,oracle,mysql,database,flask
Classifier: Development Status :: 1 - Planning
Classifier: Intended Audience :: Developers
Classifier: Programming Language :: Python :: 3
Classifier: Operating System :: Unix
Classifier: Operating System :: MacOS :: MacOS X
Classifier: Operating System :: Microsoft :: Windows
License-File: LICENSE
Requires-Dist: cx-Oracle
Requires-Dist: mysql-connector-python
